mycalc/calculator.py
ygmycalc001-0.0.1.dist-info/METADATA
ygmycalc001-0.0.1.dist-info/WHEEL
ygmycalc001-0.0.1.dist-info/top_level.txt
ygmycalc001-0.0.1.dist-info/RECORD
