Metadata-Version: 2.1
Name: ygmycalc001
Version: 0.0.1
Summary: nice calc
Home-page: https://github.com/YGC20
Download-URL: http://github.com/YGC20
Author: YGC20
License: UNKNOWN
Platform: UNKNOWN
Classifier: Programming Language :: Python :: 3
